leptons/__init__.py
leptons/agent.py
leptons/version.py
timeplus_leptons-0.0.3.dist-info/METADATA
timeplus_leptons-0.0.3.dist-info/WHEEL
timeplus_leptons-0.0.3.dist-info/top_level.txt
timeplus_leptons-0.0.3.dist-info/RECORD
