Metadata-Version: 2.1
Name: timeplus-leptons
Version: 0.0.3
Summary: Timeplus OpenAI API monitor tool
Home-page: https://github.com/timeplus-io/leptons
Author: Timeplus
Author-email: eng@timeplus.io
Classifier: License :: OSI Approved :: Apache Software License
Classifier: Programming Language :: Python :: 3.9
Requires-Dist: urllib3 >=1.15
Requires-Dist: six >=1.10
Requires-Dist: certifi
Requires-Dist: openai >=0.27.8
Requires-Dist: timeplus >=1.3.0b2
